rpy2_r6/__init__.py
rpy2_r6/r6a.py
rpy2_r6/r6b.py
rpy2_r6/tests.py
rpy2_r6/utils.py
rpy2_r6-0.0.1.dist-info/LICENSE
rpy2_r6-0.0.1.dist-info/METADATA
rpy2_r6-0.0.1.dist-info/WHEEL
rpy2_r6-0.0.1.dist-info/top_level.txt
rpy2_r6-0.0.1.dist-info/RECORD
