Metadata-Version: 2.1
Name: rpy2-r6
Version: 0.0.1
Summary: Mapping the R package R6
Author-email: Laurent Gautier <lgautier@gmail.com>
License: MIT
Project-URL: Homepage, https://rpy2.github.io/rpy2-r6/
Project-URL: Documentation, https://rpy2.github.io/rpy2-r6/version/main/html/index.html
Project-URL: Source, https://github.com/rpy2/rpy2-r6/
Project-URL: Tracker, https://github.com/rpy2/rpy2-r6/issue
Classifier: Programming Language :: Python
Classifier: Programming Language :: Python :: 3
Classifier: Programming Language :: Python :: 3.7
Classifier: Programming Language :: Python :: 3.8
Classifier: Programming Language :: Python :: 3.9
Classifier: Programming Language :: Python :: 3.10
Classifier: License :: OSI Approved :: MIT License
Classifier: Intended Audience :: Developers
Classifier: Intended Audience :: Science/Research
Classifier: Development Status :: 3 - Alpha
Requires-Python: >=3.7
License-File: LICENSE
Requires-Dist: rpy2 (>=3.5)
Provides-Extra: test
Requires-Dist: pytest ; extra == 'test'
